testable_coresvc/__init__.py
testable_coresvc/app.py
testable_coresvc/consts.py
testable_coresvc/settings.py
testable_coresvc-0.2.13.dist-info/METADATA
testable_coresvc-0.2.13.dist-info/WHEEL
testable_coresvc-0.2.13.dist-info/top_level.txt
testable_coresvc-0.2.13.dist-info/RECORD
