Metadata-Version: 2.1
Name: testable-coresvc
Version: 0.2.13
Summary: Core Testable Service Modules
Author: Ryan de Marigny
Author-email: testableproject@gmail.com
Keywords: python,testable
Classifier: Programming Language :: Python :: 3
Classifier: Operating System :: MacOS :: MacOS X
Classifier: Operating System :: Microsoft :: Windows
Requires-Dist: pydantic (>=1.10.2)
Requires-Dist: typing-extensions (>=4.4.0)
Requires-Dist: fastapi (>=0.87.0)
Requires-Dist: pymongo (>=4.3.3)
